.gitignore
.hgignore
Makefile
README.rst
setup.py
doc/Makefile
doc/source/conf.py
doc/source/index.txt
getent/__init__.py
getent/constants.py
getent/headers.py
getent/libc.py
getent.egg-info/PKG-INFO
getent.egg-info/SOURCES.txt
getent.egg-info/dependency_links.txt
getent.egg-info/top_level.txt