Metadata-Version: 1.0
Name: getent
Version: 0.2
Summary: Python interface to the POSIX getent family of commands
Home-page: UNKNOWN
Author: Wijnand Modderman-Lenstra
Author-email: maze@pyth0n.org
License: MIT
Keywords: getent group passwd shadow network alias host
Platform: UNKNOWN
